mldictionary/__init__.py
mldictionary/dictionary.py
mldictionary/english.py
mldictionary/portuguese.py
mldictionary/spanish.py
mldictionary-0.2.6.dist-info/LICENSE.md
mldictionary-0.2.6.dist-info/WHEEL
mldictionary-0.2.6.dist-info/METADATA
mldictionary-0.2.6.dist-info/RECORD
