Metadata-Version: 2.1
Name: mldictionary
Version: 0.2.6
Summary: word's dictionary for several languages
Home-page: https://pypi.org/project/mldictionary/
License: MIT
Author: Pablo Emidio
Author-email: p.emidiodev@gmail.com
Requires-Python: >=3.9,<4.0
Classifier: License :: OSI Approved :: MIT License
Classifier: Operating System :: OS Independent
Classifier: Programming Language :: Python :: 3
Classifier: Programming Language :: Python :: 3.10
Classifier: Programming Language :: Python :: 3.9
Requires-Dist: bs4 (>=0.0.1,<0.0.2)
Requires-Dist: requests (==2.25.1)
Project-URL: Repository, https://github.com/PabloEmidio/mldictionary
